bitmap_sparse_array/__init__.py
bitmap_sparse_array/py.typed
bitmap_sparse_array/sparse_array.py
bitmap_sparse_array-0.1.3.dist-info/METADATA
bitmap_sparse_array-0.1.3.dist-info/WHEEL
bitmap_sparse_array-0.1.3.dist-info/top_level.txt
bitmap_sparse_array-0.1.3.dist-info/RECORD
