Metadata-Version: 2.1
Name: bitmap_sparse_array
Version: 0.1.3
Summary: Pure python implementation of a sparse array.
Home-page: https://github.com/kralverde/py-bitmap-sparse-array/
Author: kralverde
Project-URL: Bug Tracker, https://github.com/kralverde/py-bitmap-sparse-array/issues
Classifier: Development Status :: 3 - Alpha
Classifier: Programming Language :: Python :: 3.11
Classifier: Programming Language :: Python :: 3.10
Classifier: Programming Language :: Python :: 3.9
Classifier: Programming Language :: Python :: 3.8
Classifier: Programming Language :: Python :: 3.7
Classifier: Operating System :: OS Independent
Classifier: Natural Language :: English
Classifier: Typing :: Typed
Requires-Python: >=3.7
